{
    "triplet-uuid": "96b7046f-f584-422f-a626-6f86a26dfd8b",
    "uuid": "b65549b9-fe00-43ad-a468-724d04aef134",
    "article-level-annotations": {
        "author_feeling_main_event": "neu",
        "author_feeling_Elizabeth_Lauten": "neu",
        "you_feeling_Elizabeth_Lauten": "neu",
        "author_feeling_Barack_Obama": "neu",
        "you_feeling_Barack_Obama": "neu",
        "author_feeling_Sasha_and_Malia_Obama": "neu",
        "you_feeling_Sasha_and_Malia_Obama": "neu",
        "relative_stance": "center",
        "notes": ""
    },
    "phrase-level-annotations": [
        {
            "txt": "your mother and father don’t respect their positions very much, or the nation for that matter",
            "id": "p4",
            "start": 88,
            "end": 181,
            "target": "Barack_Obama",
            "polarity": "neg",
            "aim": "dir",
            "indirect-target-name": "",
            "indirect-ally-opponent-sentiment": "",
            "bias": "inf",
            "quote": "yes",
            "speaker": "Elizabeth_Lauten",
            "notes": ""
        },
        {
            "txt": "try showing a little class",
            "id": "p1",
            "start": 126,
            "end": 152,
            "target": "Sasha_and_Malia_Obama",
            "polarity": "neg",
            "aim": "dir",
            "indirect-target-name": "",
            "indirect-ally-opponent-sentiment": "",
            "bias": "inf",
            "quote": "yes",
            "speaker": "Elizabeth_Lauten",
            "notes": ""
        },
        {
            "txt": "Dress like you deserve respect",
            "id": "p3",
            "start": 0,
            "end": 30,
            "target": "Sasha_and_Malia_Obama",
            "polarity": "neg",
            "aim": "dir",
            "indirect-target-name": "",
            "indirect-ally-opponent-sentiment": "",
            "bias": "inf",
            "quote": "yes",
            "speaker": "Elizabeth_Lauten",
            "notes": ""
        },
        {
            "txt": "took a shot",
            "id": "p4_1",
            "start": 28,
            "end": 39,
            "target": "Elizabeth_Lauten",
            "polarity": "neg",
            "aim": "dir",
            "indirect-target-name": "",
            "indirect-ally-opponent-sentiment": "",
            "bias": "lex",
            "quote": "no",
            "speaker": "",
            "notes": ""
        },
        {
            "txt": "now-deleted",
            "id": "p1",
            "start": 28,
            "end": 39,
            "target": "Elizabeth_Lauten",
            "polarity": "neg",
            "aim": "dir",
            "indirect-target-name": "",
            "indirect-ally-opponent-sentiment": "",
            "bias": "inf",
            "quote": "no",
            "speaker": "",
            "notes": ""
        },
        {
            "txt": "After many hours of prayer, talking to my parents, and re-reading my words online I can see more clearly just how hurtful my words were. ...",
            "id": "p8",
            "start": 0,
            "end": 140,
            "target": "Elizabeth_Lauten",
            "polarity": "pos",
            "aim": "dir",
            "indirect-target-name": "",
            "indirect-ally-opponent-sentiment": "",
            "bias": "inf",
            "quote": "yes",
            "speaker": "Elizabeth_Lauten",
            "notes": ""
        }
    ]
}
