{
    "triplet-uuid": "c6a0e65c-4f8b-41de-8200-cd700f683c64",
    "uuid": "8fab0133-9b78-42b9-b0c3-e35f9134a298",
    "article-level-annotations": {
        "author_feeling_main_event": "neu",
        "author_feeling_Donald_Trump": "neu",
        "you_feeling_Donald_Trump": "neu",
        "relative_stance": "conservative",
        "notes": ""
    },
    "phrase-level-annotations": [
        {
            "txt": "I would not trust the president alone with Putin without some other Americans in the administration in there",
            "id": "p11",
            "start": 1,
            "end": 109,
            "target": "Donald_Trump",
            "polarity": "neg",
            "aim": "dir",
            "indirect-target-name": "",
            "indirect-ally-opponent-sentiment": "",
            "bias": "inf",
            "quote": "yes",
            "speaker": "other_anti",
            "notes": ""
        },
        {
            "txt": "I wouldn’t trust what he says there",
            "id": "p12",
            "start": 96,
            "end": 131,
            "target": "Donald_Trump",
            "polarity": "neg",
            "aim": "dir",
            "indirect-target-name": "",
            "indirect-ally-opponent-sentiment": "",
            "bias": "inf",
            "quote": "yes",
            "speaker": "other_anti",
            "notes": ""
        },
        {
            "txt": "president’s buddy",
            "id": "p19",
            "start": 96,
            "end": 113,
            "target": "Donald_Trump",
            "polarity": "neg",
            "aim": "dir",
            "indirect-target-name": "",
            "indirect-ally-opponent-sentiment": "",
            "bias": "lex",
            "quote": "yes",
            "speaker": "other_neutral",
            "notes": ""
        },
        {
            "txt": "These indictments are further proof of what everyone but the president seems to understand",
            "id": "p7",
            "start": 1,
            "end": 91,
            "target": "Donald_Trump",
            "polarity": "neg",
            "aim": "dir",
            "indirect-target-name": "",
            "indirect-ally-opponent-sentiment": "",
            "bias": "inf",
            "quote": "yes",
            "speaker": "other_anti",
            "notes": ""
        }
    ]
}
