{
    "triplet-uuid": "84b3c118-50d2-45a5-a91f-7ed95b5d0143",
    "uuid": "b79beb25-e671-42ee-9170-9bbf3037d520",
    "article-level-annotations": {
        "author_feeling_main_event": "neg",
        "author_feeling_Donald_Trump": "neg",
        "you_feeling_Donald_Trump": "neu",
        "relative_stance": "liberal",
        "notes": ""
    },
    "phrase-level-annotations": [
        {
            "txt": "remarkable",
            "id": "p1",
            "start": 28,
            "end": 38,
            "target": "Donald_Trump",
            "polarity": "pos",
            "aim": "dir",
            "indirect-target-name": "",
            "indirect-ally-opponent-sentiment": "",
            "bias": "lex",
            "quote": "no",
            "speaker": "",
            "notes": ""
        },
        {
            "txt": "rain-soaked",
            "id": "p3",
            "start": 130,
            "end": 141,
            "target": "Donald_Trump",
            "polarity": "pos",
            "aim": "ind_pro",
            "indirect-target-name": "admirers",
            "indirect-ally-opponent-sentiment": "neu",
            "bias": "lex",
            "quote": "no",
            "speaker": "",
            "notes": ""
        },
        {
            "txt": "hostile takeover",
            "id": "p6",
            "start": 36,
            "end": 52,
            "target": "Donald_Trump",
            "polarity": "neg",
            "aim": "dir",
            "indirect-target-name": "",
            "indirect-ally-opponent-sentiment": "",
            "bias": "lex",
            "quote": "no",
            "speaker": "",
            "notes": ""
        },
        {
            "txt": "at a lobster-and-beef luncheon",
            "id": "p26",
            "start": 57,
            "end": 87,
            "target": "Donald_Trump",
            "polarity": "neg",
            "aim": "dir",
            "indirect-target-name": "",
            "indirect-ally-opponent-sentiment": "",
            "bias": "inf",
            "quote": "no",
            "speaker": "",
            "notes": ""
        },
        {
            "txt": "While large, the crowds on a soggy day did not rival the energetic throngs at Mr. Obama’s first inauguration eight years ago, according to aerial photographs.",
            "id": "p36",
            "start": 0,
            "end": 158,
            "target": "Donald_Trump",
            "polarity": "neg",
            "aim": "dir",
            "indirect-target-name": "",
            "indirect-ally-opponent-sentiment": "",
            "bias": "inf",
            "quote": "no",
            "speaker": "",
            "notes": ""
        },
        {
            "txt": "In a city that gave just 4 percent of its vote to Mr. Trump, many residents left town and about 60 House Democrats boycotted the event.",
            "id": "p38",
            "start": 0,
            "end": 135,
            "target": "Donald_Trump",
            "polarity": "neg",
            "aim": "dir",
            "indirect-target-name": "",
            "indirect-ally-opponent-sentiment": "",
            "bias": "inf",
            "quote": "no",
            "speaker": "",
            "notes": ""
        },
        {
            "txt": "The Washington Metrorail system recorded fewer than half as many rides on Friday morning as in 2009, and knots of bystanders along the inaugural parade route were not as thick.",
            "id": "p37",
            "start": 0,
            "end": 176,
            "target": "Donald_Trump",
            "polarity": "neg",
            "aim": "dir",
            "indirect-target-name": "",
            "indirect-ally-opponent-sentiment": "",
            "bias": "inf",
            "quote": "no",
            "speaker": "",
            "notes": ""
        },
        {
            "txt": "whose tumultuous love life played out in the tabloids",
            "id": "p46",
            "start": 213,
            "end": 266,
            "target": "Donald_Trump",
            "polarity": "neg",
            "aim": "dir",
            "indirect-target-name": "",
            "indirect-ally-opponent-sentiment": "",
            "bias": "inf",
            "quote": "no",
            "speaker": "",
            "notes": ""
        },
        {
            "txt": "An Ivy League-educated mogul who lives in a New York tower named after himself with an 80-foot-long living room",
            "id": "p52",
            "start": 0,
            "end": 111,
            "target": "Donald_Trump",
            "polarity": "neg",
            "aim": "dir",
            "indirect-target-name": "",
            "indirect-ally-opponent-sentiment": "",
            "bias": "inf",
            "quote": "no",
            "speaker": "",
            "notes": ""
        },
        {
            "txt": "willingness to offend whole sections of the population",
            "id": "p53",
            "start": 49,
            "end": 103,
            "target": "Donald_Trump",
            "polarity": "neg",
            "aim": "dir",
            "indirect-target-name": "",
            "indirect-ally-opponent-sentiment": "",
            "bias": "inf",
            "quote": "no",
            "speaker": "",
            "notes": ""
        },
        {
            "txt": "“this American carnage.”",
            "id": "p0",
            "start": 219,
            "end": 243,
            "target": "Donald_Trump",
            "polarity": "neg",
            "aim": "dir",
            "indirect-target-name": "",
            "indirect-ally-opponent-sentiment": "",
            "bias": "lex",
            "quote": "no",
            "speaker": "",
            "notes": ""
        },
        {
            "txt": "Mr. Trump told hundreds of thousands of rain-soaked admirers and onlookers in a forceful 16-minute Inaugural Address",
            "id": "p3_1",
            "start": 90,
            "end": 206,
            "target": "Donald_Trump",
            "polarity": "pos",
            "aim": "dir",
            "indirect-target-name": "",
            "indirect-ally-opponent-sentiment": "",
            "bias": "inf",
            "quote": "no",
            "speaker": "",
            "notes": ""
        },
        {
            "txt": "Mr. Trump’s view of the United States was strikingly grim for an Inaugural Address",
            "id": "p11",
            "start": 0,
            "end": 82,
            "target": "Donald_Trump",
            "polarity": "neg",
            "aim": "dir",
            "indirect-target-name": "",
            "indirect-ally-opponent-sentiment": "",
            "bias": "inf",
            "quote": "no",
            "speaker": "",
            "notes": ""
        },
        {
            "txt": "He later praised his defeated opponent, Hillary Clinton, at a lobster-and-beef luncheon with congressional leaders, asking her and former President Bill Clinton to stand for applause.",
            "id": "p26_1",
            "start": 0,
            "end": 183,
            "target": "Donald_Trump",
            "polarity": "pos",
            "aim": "dir",
            "indirect-target-name": "",
            "indirect-ally-opponent-sentiment": "",
            "bias": "inf",
            "quote": "no",
            "speaker": "",
            "notes": ""
        },
        {
            "txt": "“I love this country, and I don’t understand how a president of the United States that loves his country could paint a picture of its failures.”",
            "id": "p30",
            "start": 0,
            "end": 144,
            "target": "Donald_Trump",
            "polarity": "neg",
            "aim": "dir",
            "indirect-target-name": "",
            "indirect-ally-opponent-sentiment": "",
            "bias": "inf",
            "quote": "yes",
            "speaker": "other_anti",
            "notes": ""
        },
        {
            "txt": "It was interesting sitting up onstage with a bunch of billionaires hearing him say how bad the country was",
            "id": "p31",
            "start": 11,
            "end": 117,
            "target": "Donald_Trump",
            "polarity": "neg",
            "aim": "dir",
            "indirect-target-name": "",
            "indirect-ally-opponent-sentiment": "",
            "bias": "inf",
            "quote": "yes",
            "speaker": "other_anti",
            "notes": ""
        },
        {
            "txt": "raised questions about where his interests end and the country’s begin",
            "id": "p49",
            "start": 133,
            "end": 203,
            "target": "Donald_Trump",
            "polarity": "neg",
            "aim": "dir",
            "indirect-target-name": "",
            "indirect-ally-opponent-sentiment": "",
            "bias": "inf",
            "quote": "no",
            "speaker": "",
            "notes": ""
        }
    ]
}
